README.rst
setup.py
design/__init__.py
design/borders.py
design/gradients.py
design.egg-info/PKG-INFO
design.egg-info/SOURCES.txt
design.egg-info/dependency_links.txt
design.egg-info/not-zip-safe
design.egg-info/requires.txt
design.egg-info/top_level.txt