Metadata-Version: 1.1
Name: design
Version: 0.1.2
Summary: Generates various common web design elements. Borders,         patterns, textures, gradients, etc.
Home-page: https://github.com/audreyr/design
Author: Audrey Roy
Author-email: audreyr@gmail.com
License: Copyright (c) 2013, Audrey Roy
